unipressed/__init__.py
unipressed/dataset/__init__.py
unipressed/dataset/arba.py
unipressed/dataset/citations.py
unipressed/dataset/core.py
unipressed/dataset/database.py
unipressed/dataset/diseases.py
unipressed/dataset/generated_types/__init__.py
unipressed/dataset/generated_types/arba.py
unipressed/dataset/generated_types/citations.py
unipressed/dataset/generated_types/database.py
unipressed/dataset/generated_types/diseases.py
unipressed/dataset/generated_types/keywords.py
unipressed/dataset/generated_types/locations.py
unipressed/dataset/generated_types/proteomes.py
unipressed/dataset/generated_types/taxonomy.py
unipressed/dataset/generated_types/uniparc.py
unipressed/dataset/generated_types/uniprotkb.py
unipressed/dataset/generated_types/uniref.py
unipressed/dataset/generated_types/unirule.py
unipressed/dataset/keywords.py
unipressed/dataset/locations.py
unipressed/dataset/proteomes.py
unipressed/dataset/search.py
unipressed/dataset/taxonomy.py
unipressed/dataset/type_vars.py
unipressed/dataset/uniparc.py
unipressed/dataset/uniprotkb.py
unipressed/dataset/uniref.py
unipressed/dataset/unirule.py
unipressed/id_mapping/__init__.py
unipressed/id_mapping/core.py
unipressed/id_mapping/types.py
unipressed/util.py
unipressed-1.4.0.dist-info/LICENSE
unipressed-1.4.0.dist-info/METADATA
unipressed-1.4.0.dist-info/WHEEL
unipressed-1.4.0.dist-info/RECORD
