Metadata-Version: 2.1
Name: unipressed
Version: 1.4.0
Summary: Comprehensive Python client for the Uniprot REST API
Home-page: https://multimeric.github.io/Unipressed
License: MIT
Author: Michael Milton
Author-email: michael.r.milton@gmail.com
Requires-Python: >=3.8,<4.0
Classifier: License :: OSI Approved :: MIT License
Classifier: Programming Language :: Python :: 3
Classifier: Programming Language :: Python :: 3.8
Classifier: Programming Language :: Python :: 3.9
Classifier: Programming Language :: Python :: 3.10
Classifier: Programming Language :: Python :: 3.11
Classifier: Programming Language :: Python :: 3.12
Requires-Dist: requests (>=2.28.1,<3.0.0)
Requires-Dist: typing-extensions (>=4.3.0,<5.0.0)
Project-URL: Repository, https://github.com/multimeric/Unipressed
